README.rst
setup.py
asyncio_dispatch/__init__.py
asyncio_dispatch/dispatcher.py
asyncio_dispatch.egg-info/PKG-INFO
asyncio_dispatch.egg-info/SOURCES.txt
asyncio_dispatch.egg-info/dependency_links.txt
asyncio_dispatch.egg-info/top_level.txt