Metadata-Version: 1.1
Name: asyncio-dispatch
Version: 1.0.0
Summary: asyncio_dispatch is a is a signal dispatcher for the ``asyncio`` event loop found in Python versions 3.4 and up.
Home-page: https://github.com/lenzenmi/asyncio_dispatch/
Author: Mike Lenzen
Author-email: lenzenmi@gmail.com
License: UNKNOWN
Keywords: asyncio_dispatch asyncio dispatch signal event
Platform: UNKNOWN
Classifier: License :: OSI Approved :: MIT License
Classifier: Intended Audience :: Developers
Classifier: Programming Language :: Python :: 3.4
Classifier: Topic :: Software Development :: Libraries
Classifier: Development Status :: 4 - Beta
